[
  {
    "author": "@mlb",
    "media": "instagram",
    "caption": "The @Padres have #CLINCHED their ticket to the #postseason! \ud83d\udea8",
    "date": "09-24-24",
    "likes": 94129,
    "link": "https://www.instagram.com/p/DAU9eo3uUP_/?utm_source=ig_web_copy_link&igsh=MzRlODBiNWFlZA==",
    "tagged": [
      "@mannymachado",
      "@_jacksonmerrill_",
      "@arraezluis",
      "@dylancease7",
      "@padres",
      "@budweiserusa"
    ]
  },
  {
    "author": "@mlb",
    "media": "instagram",
    "caption": "The 2024 #WorldSeries champion will be the .... ?",
    "date": "10-01-24",
    "likes": 160194,
    "link": "https://www.instagram.com/p/DAlkVWSxpEW/?utm_source=ig_web_copy_link&igsh=MzRlODBiNWFlZA==",
    "tagged": []
  },
  {
    "author": "@dodgers",
    "media": "instagram",
    "caption": "RIIZE up, Dodger Stadium. Thanks for a great performance, @riize_official!",
    "date": "05-22-24",
    "likes": 96119,
    "link": "https://www.instagram.com/p/C7TAamftOgg/?utm_source=ig_web_copy_link&igsh=MzRlODBiNWFlZA==",
    "tagged": [
      "@riize_official"
    ],
    "team name": "los angeles dodgers"
  },
  {
    "author": "@dodgers",
    "media": "instagram",
    "caption": "Views from the World Series Parade! \ud83c\udfc6",
    "date": "11-01-24",
    "likes": 600485,
    "link": "https://www.instagram.com/p/DB2XHpRSSBZ/?utm_source=ig_web_copy_link",
    "tagged": [
      "@kikehndez",
      "@claytonkershaw",
      "@miggyslocker",
      "@will.smith",
      "@jflare",
      "@alexvesia",
      "@brusdar14graterol",
      "@shoheiohtani",
      "@elchino242",
      "@mookiebetts"
    ],
    "team name": "los angeles dodgers"
  },
  {
    "author": "@padres",
    "media": "instagram",
    "caption": "Dylan\u2019s ready to deal \ud83d\udcaa",
    "date": "10-04-24",
    "likes": 50947,
    "link": "https://www.instagram.com/p/DAt5G4-zIJV/?utm_source=ig_web_copy_link&igsh=MzRlODBiNWFlZA==",
    "tagged": [
      "@dylancease7",
      "@mlb"
    ],
    "team name": "san diego padres"
  },
  {
    "author": "@dbacks",
    "media": "instagram",
    "caption": "CorbHIM.",
    "date": "08-28-24",
    "likes": 27439,
    "link": "https://www.instagram.com/p/C_Peuk3Rz8m/?utm_source=ig_web_copy_link&igsh=MzRlODBiNWFlZA==",
    "tagged": [
      "@corbin.carroll",
      "@geraldoperdomo93"
    ],
    "team name": "arizona diamondbacks"
  },
  {
    "author": "@braves", 
    "media": "instagram",
    "caption": "That\u2019s Duvall, folks!",
    "date": "06-29-24",
    "likes": 50858,
    "link": "https://www.instagram.com/p/C80V3OtuogH/?utm_source=ig_web_copy_link&igsh=MzRlODBiNWFlZA==",
    "tagged": [
      "@aduvall1234"
    ],
    "team name": "atlanta braves"
  },
  {
    "author": "@braves",
    "media": "instagram",
    "caption": "Series win!",
    "date": "11-22-24",
    "likes": 30963,
    "link": "https://www.instagram.com/p/DAO5uinywlK/?utm_source=ig_web_copy_link&igsh=MzRlODBiNWFlZA==",
    "tagged": [],
    "team name": "atlanta braves"
  },
  {
    "author": "@orioles",
    "media": "instagram",
    "caption": "Districtly Business",
    "date": "08-14-24",
    "likes": 30963,
    "link": "https://www.instagram.com/p/C-rAh2yp-qo/?utm_source=ig_web_copy_link&igsh=MzRlODBiNWFlZA==",
    "tagged": [
      "@g_henderson002",
      "@coltoncowser"
    ],
    "team name": "baltimore orioles"
  },
  {
    "author": "@orioles",
    "media": "instagram",
    "caption": "Angry walks >",
    "date": "09-04-24",
    "likes": 21595,
    "link": "https://www.instagram.com/reel/C_gVfX3OF1j/?utm_source=ig_web_copy_link&igsh=MzRlODBiNWFlZA==",
    "tagged": [
      "@g_henderson002",
      "@mlbcut4"
    ],
    "team name": "baltimore orioles"
  },
  {
    "author": "@redsox",
    "media": "instagram",
    "caption": "To the second deck!",
    "date": "08-21-24",
    "likes": 24191,
    "link": "https://www.instagram.com/p/C-8hxwRR5cP/?utm_source=ig_web_copy_link",
    "tagged": [
      "@d_ham27",
      "@duranjarren"
    ],
    "team name": "boston red sox"
  },
  {
    "author": "@redsox",
    "media": "instagram",
    "caption": "HAVE A DAY, NICK!",
    "date": "06-05-24",
    "likes": 13295,
    "link": "https://www.instagram.com/p/C72MY4exFhx/?utm_source=ig_web_copy_link&igsh=MzRlODBiNWFlZA==",
    "tagged": [
      "@npivetta43"
    ],
    "team name": "boston red sox"
  },
  {
    "author": "@cubs",
    "media": "instagram",
    "caption": "endless gratitude for the greatest fans in the world.",
    "date": "11-28-24",
    "likes": 10439,
    "link": "https://www.instagram.com/p/DC62tNWRofg/?utm_source=ig_web_copy_link",
    "tagged": [],
    "team name": "chicago cubs"
  },
  {
    "author": "@reds",
    "media": "instagram",
    "caption": "One more for \u201824",
    "date": "09-29-24",
    "likes": 17498,
    "link": "https://www.instagram.com/p/DAhKhwNA3kg/?utm_source=ig_web_copy_link&igsh=MzRlODBiNWFlZA==",
    "tagged": [
      "@la_cocoa_____18",
      "@therealhuntergreene",
      "@jonathan_india",
      "@tonysantillan2"
    ],
    "team name": "cincinnati reds"
  },
  {
    "author": "@cleguardians",
    "media": "instagram",
    "caption": "It\u2019s now or never. #ForTheLand | #GuardsBall",
    "date": "10-10-24",
    "likes": 10557,
    "link": "https://www.instagram.com/p/DA8xVTnOzX8/?utm_source=ig_web_copy_link&igsh=MzRlODBiNWFlZA==",
    "tagged": [],
    "team name": "cleveland guardians"
  },
  {
    "author": "@cleguardians",
    "media": "instagram",
    "caption": "Feels good to be back in the win column! #ForTheLand",
    "date": "07-23-24",
    "likes": 13459,
    "link": "https://www.instagram.com/p/C9yWa54sM-a/?utm_source=ig_web_copy_link&igsh=MzRlODBiNWFlZA==",
    "tagged": [
      "@ramirez_jose11",
      "@jaynaylor10",
      "@jhonkensy"
    ],
    "team name": "cleveland guardians"
  },
  {
    "author": "@rockies",
    "media": "instagram",
    "caption": "Got the series W \ud83d\udcaa",
    "date": "05-11-24",
    "likes": 11279,
    "link": "https://www.instagram.com/p/C62rlZ7OeVX/?utm_source=ig_web_copy_link",
    "tagged": [
      "@chuck__nazty",
      "@rymcmahon"
    ],
    "team name": "colorado rockies"
  },
  {
    "author": "@rockies",
    "media": "instagram",
    "caption": "Happy birthday Goody! \ud83c\udf89",
    "date": "10-08-24",
    "likes": 1786,
    "link": "https://www.instagram.com/p/C62rlZ7OeVX/?utm_source=ig_web_copy_link",
    "tagged": [
      "@hgoody35"
    ],
    "team name": "colorado rockies"
  },
  {
    "author": "@tigers",
    "media": "instagram",
    "caption": "Getting us started in Cleveland \ud83d\udcaa",
    "date": "10-05-24",
    "likes": 19519,
    "link": "https://www.instagram.com/tigers/p/DAvgQM1xZhK/",
    "tagged": [
      "@tholt14",
      "@mlb",
      "@tarikskubal"
    ],
    "team name": "detroit tigers"
  },
  {
    "author": "@tigers",
    "media": "instagram",
    "caption": "Great opportunity to be great.",
    "date": "10-11-24",
    "likes": 17857,
    "link": "https://www.instagram.com/p/DA_5untvs6Q/?utm_source=ig_web_copy_link&igsh=MzRlODBiNWFlZA==",
    "tagged": [
      "@tarikskubal"
    ],
    "team name": "detroit tigers"
  },
  {
    "author": "@astros",
    "media": "instagram",
    "caption": "Welcome to H-Town, @yuseik18!",
    "date": "07-29-24",
    "likes": 22697,
    "link": "https://www.instagram.com/p/C-CBV-SgkV7/?utm_source=ig_web_copy_link&igsh=MzRlODBiNWFlZA==",
    "tagged": [],
    "team name": "houston astros"
  },
  {
    "author": "@kcroyals",
    "media": "instagram",
    "caption": "Got what we needed. #HEYHEYHEYHEY",
    "date": "09-24-24",
    "likes": 13408,
    "link": "https://www.instagram.com/p/DAUxl1pRX1N/?utm_source=ig_web_copy_link&igsh=MzRlODBiNWFlZA==",
    "tagged": [],
    "team name": "kansas city royals"
  },
  {
    "author": "@kcroyals",
    "media": "instagram",
    "caption": "Special September Saturday. #HEYHEYHEYHEY",
    "date": "09-07-24",
    "likes": 13942,
    "link": "https://www.instagram.com/p/C_o57C3J5Dr/?utm_source=ig_web_copy_link&igsh=MzRlODBiNWFlZA==",
    "tagged": [
      "@lucas.erceg",
      "@kyle_isbel",
      "@tphamlv",
      "@bwitter7",
      "@mjmelendez"
    ],
    "team name": "kansas city royals"
  },
  {
    "author": "@angels",
    "media": "instagram",
    "caption": "stars & stripes \ud83c\uddfa\ud83c\uddf8",
    "date": "07-04-24",
    "likes": 14619,
    "link": "https://www.instagram.com/p/C9A6pq-SaM0/?utm_source=ig_web_copy_link&igsh=MzRlODBiNWFlZA==",
    "tagged": [
      "@logan_ohoppe",
      "@kpillar11",
      "@adell7"
    ],
    "team name": "los angeles angels"
  },
  {
    "author": "@angels",
    "media": "instagram",
    "caption": "smile! it\u2019s team photo day! \ud83d\udcf8",
    "date": "08-31-24",
    "likes": 15890,
    "link": "https://www.instagram.com/p/C_WmizjyQXN/?utm_source=ig_web_copy_link&igsh=MzRlODBiNWFlZA==",
    "tagged": [
      "@logan_ohoppe",
      "@mickeymoniak",
      "@zachneto2",
      "@soriano_24_rd"
    ],
    "team name": "los angeles angels"
  },
  {
    "author": "@dodgers",
    "media": "instagram",
    "caption": "Opening Day ready.",
    "date": "03-28-24",
    "likes": 197914,
    "link": "https://www.instagram.com/p/C5EZrtSvRB4/?utm_source=ig_web_copy_link&igsh=MzRlODBiNWFlZA==",
    "tagged": [
      "@shoheiohtani",
      "@mookiebetts",
      "@glasnowt"
    ],
    "team name": "los angeles dodgers"
  },
  {
    "author": "@marlins",
    "media": "instagram",
    "caption": "making his mlb debut:",
    "date": "05-05-2024",
    "likes": 4068,
    "link": "https://www.instagram.com/p/C6mvJ2SADZA/?utm_source=ig_web_copy_link&igsh=MzRlODBiNWFlZA==",
    "tagged": [
      "@eli_villalobos20"
    ],
    "team name": "miami marlins"
  },
  {
    "author": "@brewers",
    "media": "instagram",
    "caption": "Coming for that crown \ud83d\udc51",
    "date": "09-26-24",
    "likes": 11794,
    "link": "https://www.instagram.com/p/DAAGZevuoNw/?utm_source=ig_web_copy_link&igsh=MzRlODBiNWFlZA==",
    "tagged": [
      "@bturang1"
    ],
    "team name": "milwaukee brewers"
  },
  {
    "author": "@twins",
    "media": "instagram",
    "caption": "Max making a splash tonight!",
    "date": "06-24-24",
    "likes": 11794,
    "link": "https://www.instagram.com/p/C8OATmmskoY/?utm_source=ig_web_copy_link&igsh=MzRlODBiNWFlZA==",
    "tagged": [
      "@teamcjcorrea"
    ],
    "team name": "minnesota twins"
  },
  {
    "author": "@mets",
    "media": "instagram",
    "caption": "We\u2019ve had a pretty crazy 10 days! \ud83e\udd2f What\u2019s been your favorite moment, so far?",
    "date": "10-11-24",
    "likes": 41193,
    "link": "https://www.instagram.com/p/DBAM-FtxaE8/?utm_source=ig_web_copy_link&igsh=MzRlODBiNWFlZA==",
    "tagged": [
      "@lindor12bc",
      "@bnimmo24",
      "@marte06"
    ],
    "team name": "new york mets"
  },
  {
    "author": "@mets",
    "media": "instagram",
    "caption": "California, here we come! \ud83e\udd29",
    "date": "10-12-24",
    "likes": 54479,
    "link": "https://www.instagram.com/p/DBCNj6-RNpN/?utm_source=ig_web_copy_link&igsh=MzRlODBiNWFlZA==",
    "tagged": [
      "@lindor12bc",
      "@markvientos",
      "rstanek_55"
    ],
    "team name": "new york mets"
  },
  {
    "author": "@yankees",
    "media": "instagram",
    "caption": "We\u2019ll see you at our place tonight.",
    "date": "10-05-24",
    "likes": 127735,
    "link": "https://www.instagram.com/reel/DAveDTwxuia/?utm_source=ig_web_copy_link&igsh=MzRlODBiNWFlZA==",
    "tagged": [],
    "team name": "new york yankees"
  },
  {
    "author": "@yankees",
    "media": "instagram",
    "caption": "That was loud.",
    "date": "06-16-24",
    "likes": 112145,
    "link": "https://www.instagram.com/p/C8S6BSzuZX_/?utm_source=ig_web_copy_link&igsh=MzRlODBiNWFlZA==",
    "tagged": [],
    "team name": "new york yankees"
  },
  {
    "author": "@yankees",
    "media": "instagram",
    "caption": "Yay Area.",
    "date": "06-02-24",
    "likes": 164351,
    "link": "https://www.instagram.com/p/C7u1FXFvq7d/?utm_source=ig_web_copy_link&igsh=MzRlODBiNWFlZA==",
    "tagged": [
      "@juansoto_25"
    ],
    "team name": "new york yankees"
  },
  {
    "author": "@athletics",
    "media": "instagram",
    "caption": "Happy B-day @osvaldobido!! \ud83c\udf89",
    "date": "10-18-24",
    "likes": 1467,
    "link": "https://www.instagram.com/p/DBRYwIZJI7T/?utm_source=ig_web_copy_link&igsh=MzRlODBiNWFlZA==",
    "tagged": [
      "@osvaldobido"
    ],
    "team name": "oakland athletics"
  },
  {
    "author": "@mlb",
    "media": "instagram",
    "caption": "The @Athletics win the final game at the Coliseum",
    "date": "09-26-24",
    "likes": 176210,
    "link": "https://www.instagram.com/p/DAZenKfuV06/?utm_source=ig_web_copy_link&igsh=MzRlODBiNWFlZA==",
    "tagged": [
      "@athletics",
      "@mason.j.miller"
    ]
  },
  {
    "author": "@phillies",
    "media": "instagram",
    "caption": "Your 2024 National League East Champions \u2764\ufe0f",
    "date": "09-23-24",
    "likes": 108801,
    "link": "https://www.instagram.com/p/DASCnC-sA50/?utm_source=ig_web_copy_link&igsh=MzRlODBiNWFlZA==",
    "tagged": [],
    "team name": "philadelphia phillies"
  },
  {
    "author": "@phillies",
    "media": "instagram",
    "caption": "WE GOT OURSELVES A NEW SERIES IN NEW YORK",
    "date": "10-06-24",
    "likes": 65588,
    "link": "https://www.instagram.com/p/DAzT5epuBKf/",
    "tagged": [
      "@casty_8"
    ],
    "team name": "philadelphia phillies"
  },
  {
    "author": "@pittsburghpirates",
    "media": "instagram",
    "caption": "First of many.",
    "date": "05-11-24",
    "likes": 65585,
    "link": "https://www.instagram.com/p/C613_6CvVXc/?utm_source=ig_web_copy_link&igsh=MzRlODBiNWFlZA==",
    "tagged": [
      "@mlb",
      "@paulskenes"
    ],
    "team name": "pittsburgh pirates"
  },
  {
    "author": "@pittsburghpirates",
    "media": "instagram",
    "caption": "Past, present and future.",
    "date": "08-24-24",
    "likes": 8304,
    "link": "https://www.instagram.com/p/C_EYA-NSYgB/?utm_source=ig_web_copy_link&igsh=MzRlODBiNWFlZA==",
    "tagged": [
      "@blbonds25",
      "@cutchtwenty2",
      "@paulskenes",
      "@derekshelton17"
    ],
    "team name": "pittsburgh pirates"
  },
  {
    "author": "@padres",
    "media": "instagram",
    "caption": "We teamed up with @usaa to host an on-field baseball camp for #SDMilitary families at @petcopark today!",
    "date": "07-29-24",
    "likes": 6351,
    "link": "https://www.instagram.com/p/C-BjXbxyq9W/?utm_source=ig_web_copy_link&igsh=MzRlODBiNWFlZA==",
    "tagged": [
      "@usaa",
      "@khigashioka",
      "@stephenkolek"
    ],
    "team name": "san diego padres"
  },
  {
    "author": "@sfgiants",
    "media": "instagram",
    "caption": "Snellzilla is coming\u2026",
    "date": "04-08-24",
    "likes": 56089,
    "link": "https://www.instagram.com/p/C5geCftLWF8/?utm_source=ig_web_copy_link&igsh=MzRlODBiNWFlZA==",
    "tagged": [
      "@snellzilla4",
      "@mlb"
    ],
    "team name": "san francisco giants"
  },
  {
    "author": "@sfgiants",
    "media": "instagram",
    "caption": "It\u2019s a walk-off",
    "date": "07-09-24",
    "likes": 41686,
    "link": "https://www.instagram.com/p/C9OtJNDxooV/?utm_source=ig_web_copy_link&igsh=MzRlODBiNWFlZA==",
    "tagged": [
      "@tylerfitzgerald10"
    ],
    "team name": "san francisco giants"
  },
  {
    "author": "@mariners",
    "media": "instagram",
    "caption": "It is Win-sday my dudes. #TridentsUp \ud83d\udd31",
    "date": "05-15-24",
    "likes": 15407,
    "link": "https://www.instagram.com/p/C9OtJNDxooV/?utm_source=ig_web_copy_link&igsh=MzRlODBiNWFlZA==",
    "tagged": [
      "@tyfrance",
      "@calraleigh_",
      "@bwpp.2"
    ],
    "team name": "seattle mariners"
  },
  {
    "author": "@cardinals",
    "media": "instagram",
    "caption": "Connected to this city.",
    "date": "05-20-24",
    "likes": 264658,
    "link": "https://www.instagram.com/p/C7NjGeSsQna/?utm_source=ig_web_copy_link&igsh=MzRlODBiNWFlZA==",
    "tagged": [
      "@metroboomin",
      "@mlb"
    ],
    "team name": "st. louis cardinals"
  },
  {
    "author": "@raysbaseball",
    "media": "instagram",
    "caption": "We are thrilled to play in Tampa Bay. \ud83e\ude75 To be the first to receive ticketing information, join the 2025 Interest List at the link in our bio.",
    "date": "11-14-24",
    "likes": 71159,
    "link": "https://www.instagram.com/p/DCXBmrqRC1c/?utm_source=ig_web_copy_link&igsh=MzRlODBiNWFlZA==",
    "tagged": [
      "@mlb"
    ],
    "team name": "tampa bay rays"
  },
  {
    "author": "@raysbaseball",
    "media": "instagram",
    "caption": "To our Rays family, fans and the entire Tampa Bay community. \ud83e\ude75",
    "date": "10-10-24",
    "likes": 18718,
    "link": "https://www.instagram.com/p/DA87PbdxWG2/?utm_source=ig_web_copy_link&igsh=MzRlODBiNWFlZA==",
    "tagged": [
      "@tropicanafield"
    ],
    "team name": "tampa bay rays"
  },
  {
    "author": "@rangers",
    "media": "instagram",
    "caption": "Our team, our place.",
    "date": "07-16-24",
    "likes": 21193,
    "link": "https://www.instagram.com/p/C9ge0DIspXB/?utm_source=ig_web_copy_link&igsh=MzRlODBiNWFlZA==",
    "tagged": [
      "@kirbskauai"
    ],
    "team name": "texas rangers"
  },
  {
    "author": "@rangers",
    "media": "instagram",
    "caption": "1st career homer is an inside-the-parker for @wyattlangford8!",
    "date": "04-28-24",
    "likes": 74023,
    "link": "https://www.instagram.com/p/C6USNtYx0vo/?utm_source=ig_web_copy_link",
    "tagged": [
      "@mlb",
      "@wyattlangford8"
    ],
    "team name": "texas rangers"
  },
  {
    "author": "@bluejays",
    "media": "instagram",
    "caption": "An unforgettable night for Will Wagner and the Wagner Family \u2764\ufe0f\ud83d\udc99 #TOTHECORE",
    "date": "08-13-24",
    "likes": 19072,
    "link": "https://www.instagram.com/p/C-ncpQHPL5y/?utm_source=ig_web_copy_link",
    "tagged": [
      "@buffalobisons",
      "@mlb",
      "@sportsnet",
      "@milb"
    ],
    "team name": "toronto blue jays"
  },
  {
    "author": "@nationals",
    "media": "instagram",
    "caption": "\u2764\ufe0f",
    "date": "09-30-24",
    "likes": 9579,
    "link": "https://www.instagram.com/p/DAjB1RzO1Pc/?utm_source=ig_web_copy_link",
    "tagged": [],
    "team name": "washington nationals"
  },
  {
    "author": "@nationals",
    "media": "instagram",
    "caption": "now CLAP",
    "date": "09-24-24",
    "likes": 1582,
    "link": "https://www.instagram.com/p/DAUan0_ug4B/?utm_source=ig_web_copy_link",
    "tagged": [
      "@nasimnunez",
      "@jacob_young27"
    ],
    "team name": "washington nationals"
  }
]